README.md
setup.cfg
setup.py
shamus/__init__.py
shamus/shamus.py
shamus/term_colors.py
shamus/utils.py
shamus/warning_levels.py
shamus.egg-info/PKG-INFO
shamus.egg-info/SOURCES.txt
shamus.egg-info/dependency_links.txt
shamus.egg-info/not-zip-safe
shamus.egg-info/requires.txt
shamus.egg-info/top_level.txt