Metadata-Version: 2.1
Name: shamus
Version: 0.6
Summary: Small python decorator for basic method time and memory usage.
Home-page: https://github.com/marinko-peso/shamus
Author: Marinko Peso
Author-email: marinko.peso@gmail.com
License: MIT
Keywords: decorator memory time method
Platform: UNKNOWN
Classifier: Intended Audience :: Developers
Classifier: License :: OSI Approved :: MIT License
Classifier: Operating System :: OS Independent
Classifier: Programming Language :: Python
Classifier: Programming Language :: Python :: 2
Classifier: Programming Language :: Python :: 2.7
Classifier: Programming Language :: Python :: 3
Classifier: Programming Language :: Python :: 3.6
